[
    {
        "lat": 38.3717950,
        "long": -110.7045599,
        "note": "Sample Cash"
    },
    {
        "lat": 38.3717950,
        "long": -110.7045599,
        "note": "Rock locations?"
    },
    {
        "lat": 38.3717950,
        "long": -110.7045599,
        "note": "Rock Box"
    },
    {
        "lat": 38.3717950,
        "long": -110.7045599,
        "note": "Astronaout"
    },
    {
        "lat": 38.3717950,
        "long": -110.7045599,
        "note": "Work Area"
    },
    {
        "lat": 38.3717950,
        "long": -110.7045599,
        "note": "Wrekage Site"
    },
    {
        "lat": 38.3717950,
        "long": -110.7045599,
        "note": "6A: Far Wrekage Site"
    },
    {
        "lat": 38.3717950,
        "long": -110.7045599,
        "note": "Drone"
    }
]
